azcmd/__init__.py
azcmd/azblob.py
azcmd/azpg.py
azcmd/funcs.py
azcmd/models.py
azcmd-0.1.1.dist-info/LICENSE
azcmd-0.1.1.dist-info/METADATA
azcmd-0.1.1.dist-info/WHEEL
azcmd-0.1.1.dist-info/entry_points.txt
azcmd-0.1.1.dist-info/RECORD
