Metadata-Version: 2.1
Name: azcmd
Version: 0.1.1
Summary: Simplify dealing with Azure Blob Storages.
License: MIT
Author: Jason Viloria
Author-email: jnvilo@gmail.com
Requires-Python: >=3.8,<4.0
Classifier: License :: OSI Approved :: MIT License
Classifier: Programming Language :: Python :: 3
Classifier: Programming Language :: Python :: 3.8
Classifier: Programming Language :: Python :: 3.9
Classifier: Programming Language :: Python :: 3.10
Classifier: Programming Language :: Python :: 3.11
Requires-Dist: azure-identity (>=1.15.0,<2.0.0)
Requires-Dist: azure-mgmt-resource (>=23.0.1,<24.0.0)
Requires-Dist: azure-storage-blob (>=12.18.3,<13.0.0)
